Workbook

Sheet Catalogue
A1: Issuer | B1: Status | C1: Card | D1: Base reward | E1: Accelerated rewards | F1: Reward-point value | G1: Monthly/quarterly/annual caps | H1: Minimum transaction | I1: Excluded categories/MCCs | J1: Excluded merchants | K1: Joining fee | L1: Annual fee | M1: Fee-waiver condition | N1: Forex markup | O1: Lounge benefits | P1: Milestone benefits | Q1: Fuel surcharge waiver | R1: Other benefits | S1: Official source URL | T1: Effective date | U1: Reward source URL | V1: Reward source type | W1: Reward research date | X1: Reward research note
A2: HDFC Bank | B2: Selectable | C2: Millennia Credit Card | D2: 1% CashPoints on eligible spends. | E2: 5% CashPoints on Amazon, Flipkart, Myntra, Tata CLiQ, Swiggy, Zomato, Uber, BookMyShow, Sony LIV and Cult.fit. | F2: 1 CashPoint = ₹1 for statement cashback; ₹0.30 for flights/hotels, airmiles and catalogue redemptions. | G2: Statement cashback redemption max 3,000 CashPoints/month; flights/hotels redemption max 50,000 CashPoints/month. Quarterly milestone at ₹1 lakh eligible spend. | K2: ₹1,000 + applicable taxes | L2: ₹1,000 + applicable taxes | M2: Annual fee waived on ₹1 lakh eligible annual spend. | O2: Quarterly milestone choice can include 1 domestic lounge visit instead of ₹1,000 voucher after ₹1 lakh quarterly spend. | P2: ₹1,000 voucher OR 1 domestic lounge visit on ₹1 lakh spend in a calendar quarter. | Q2: 1% waiver on fuel transactions of ₹400–₹5,000; max ₹250 per statement cycle. | S2: https://www.hdfc.bank.in/credit-cards/millennia-credit-card https://www.hdfc.bank.in/credit-cards | T2: Current product page accessed 2026-09-09
A3: HDFC Bank | B3: Selectable | C3: IndianOil HDFC Bank Credit Card | D3: 1 Fuel Point per ₹150 on eligible other spends, including eligible UPI spends. | E3: 5% Fuel Points on eligible IndianOil fuel, groceries and bill payments. | F3: 1 Fuel Point = 3 IndianOil XTRAREWARDS points; issuer indicates approx. ₹0.96 fuel value and ₹0.20 for catalogue/cashback redemption. | G3: IndianOil fuel: 250 Fuel Points/month for first 6 months, then 150/month; grocery: 100/month; bill payments: 100/month. | S3: https://www.hdfc.bank.in/credit-cards | T3: Current official catalogue accessed 2026-09-09 | U3: https://www.hdfc.bank.in/credit-cards/indianoil-hdfc-bank-credit-card | V3: Official issuer | W3: 2026-09-09 | X3: Second-pass reward/cashback research; populated only from located source material.
A4: HDFC Bank | B4: Selectable | C4: Tata Neu Infinity HDFC Bank Credit Card | D4: 1.5% NeuCoins on eligible non-Tata spends. | E4: 5% NeuCoins on eligible Tata brand spends plus an additional 5% on select Tata Neu transactions; eligible UPI spends earn up to 1.5%. | F4: 1 NeuCoin = ₹1 when redeemed in the Tata Neu ecosystem. | G4: UPI reward component capped at 500 NeuCoins per calendar month. | S4: https://www.hdfc.bank.in/credit-cards | T4: Current official catalogue accessed 2026-09-09 | U4: https://www.hdfc.bank.in/credit-cards/tata-neu-infinity-hdfc-bank-credit-card | V4: Official issuer | W4: 2026-09-09 | X4: Second-pass reward/cashback research; populated only from located source material.
A5: HDFC Bank | B5: Selectable | C5: HDFC Bank MoneyBack+ Credit Card | D5: 2 CashPoints per ₹150 on eligible spends. | E5: 10X CashPoints (20 CashPoints per ₹150) at Amazon, BigBasket, Flipkart, Reliance Smart SuperStore and Swiggy. | G5: Accelerated rewards capped at 2,500 CashPoints/month; total reward accrual capped at 15,000 CashPoints per statement cycle. | I5: Fuel, EMI, rent, government, wallet/gift/prepaid/voucher; education through third-party apps excluded; wallet and EasyEMI excluded. | P5: ₹500 gift voucher at ₹50,000 eligible spend in a calendar quarter; joining/renewal fee payment benefit of 500 CashPoints where applicable. | S5: https://www.hdfc.bank.in/credit-cards/moneyback-plus-credit-card https://www.hdfc.bank.in/credit-cards | T5: Current official product/T&C accessed 2026-09-09
A6: HDFC Bank | B6: Selectable | C6: HDFC Bank Freedom Credit Card | D6: 1 Reward Point per ₹200 on eligible spends. | E6: 10X Reward Points at select partners including BigBasket, BookMyShow, OYO, Swiggy and Uber, subject to current issuer terms. | F6: 1 Reward Point = up to about ₹0.15 for cashback redemption; value varies by redemption option. | S6: https://www.hdfc.bank.in/credit-cards | T6: Current official catalogue accessed 2026-09-09 | U6: https://www.hdfc.bank.in/credit-cards/freedom-credit-card | V6: Official issuer | W6: 2026-09-09 | X6: Second-pass reward/cashback research; populated only from located source material.
A7: HDFC Bank | B7: Selectable | C7: PhonePe HDFC Bank Uno Credit Card | D7: 1% value back on eligible scan-and-pay/UPI spends, subject to card terms. | E7: 2% on eligible PhonePe categories and 1% on select online spends; cashback/reward buckets are separately capped. | F7: 1 Reward Point = ₹1 for cashback redemption; about ₹0.30 on selected SmartBuy redemptions. | G7: Up to 500 Reward Points/month in each of the PhonePe, select-online and scan-and-pay buckets, as applicable. | S7: https://www.hdfc.bank.in/credit-cards | T7: Current official catalogue accessed 2026-09-09 | U7: https://www.hdfc.bank.in/credit-cards/phonepe-hdfc-bank-uno-credit-card | V7: Official issuer | W7: 2026-09-09 | X7: Second-pass reward/cashback research; populated only from located source material.
A8: HDFC Bank | B8: Selectable | C8: PhonePe HDFC Bank Ultimo Credit Card | D8: 1% value back on eligible scan-and-pay/UPI spends. | E8: 10% on eligible PhonePe recharge, utility, bill-payment and travel spends; 5% on select online merchants such as Amazon, Flipkart, Myntra, AJIO, Swiggy, Zomato and Uber. | F8: 1 Reward Point = ₹1 for cashback redemption; about ₹0.30 on selected SmartBuy redemptions. | G8: PhonePe 10% bucket: up to 1,000 Reward Points/month; select-online 5% bucket: up to 500/month; scan-and-pay: up to 500/month. | S8: https://www.hdfc.bank.in/credit-cards | T8: Current official catalogue accessed 2026-09-09 | U8: https://www.hdfc.bank.in/credit-cards/phonepe-hdfc-bank-ultimo-credit-card | V8: Official issuer | W8: 2026-09-09 | X8: Second-pass reward/cashback research; populated only from located source material.
A9: HDFC Bank | B9: Selectable | C9: HDFC Bank Diners Club Black Metal Edition Credit Card | D9: 5 Reward Points per ₹150 on eligible retail spends. | E9: 2X Reward Points on eligible weekend dining and up to 10X through eligible SmartBuy offers. | F9: Up to ₹1/point for eligible flight/hotel redemptions; airline-mile transfer can be up to 1:1; catalogue about ₹0.50 and cashback about ₹0.30 per point. | G9: Accelerated SmartBuy rewards subject to programme caps; quarterly milestone: 10,000 bonus Reward Points on ₹4 lakh eligible quarterly spend. | S9: https://www.hdfc.bank.in/credit-cards | T9: Current official catalogue accessed 2026-09-09 | U9: https://v.hdfc.bank.in/htdocs/amp/personal/pay/cards/credit-cards/diners-club-black-metal-edition.html | V9: Official issuer | W9: 2026-09-09 | X9: Second-pass reward/cashback research; populated only from located source material.
A10: HDFC Bank | B10: Selectable | C10: HDFC Bank PIXEL Play Credit Card | D10: 1% cashback/reward value on eligible spends. | E10: 5% on chosen benefit packs, 5% through eligible SmartBuy spends, 3% on eligible e-commerce and 1% on eligible UPI spends. | G10: Issuer T&C provides separate monthly caps, commonly up to ₹500 in each accelerated bucket. | K10: ₹500 (published card fee; fee-waiver conditions may apply). | L10: ₹500 | M10: Joining fee waiver at ₹20,000 eligible spend in first 90 days; renewal fee waiver at ₹1 lakh annual spend. | S10: https://www.hdfc.bank.in/credit-cards | T10: Current HDFC PIXEL MITC/product material accessed 2026-09-09 | U10: https://www.hdfc.bank.in/content/dam/hdfcbankpws/in/en/personal-banking/discover-products/cards/credit-cards/pixel-play-credit-card/terms-and-conditions-pixel-play-credit-card-16122025.pdf | V10: Official issuer | W10: 2026-09-09 | X10: Second-pass reward/cashback research; populated only from located source material.
A11: HDFC Bank | B11: Selectable | C11: HDFC Bank PIXEL Go Credit Card | D11: 1% cashback/reward value on eligible spends. | E11: 5% on eligible SmartBuy transactions and 1% on eligible UPI transactions. | K11: ₹250 (published card fee; fee-waiver conditions may apply). | L11: ₹250 | M11: Joining fee waiver at ₹10,000 eligible spend in first 90 days. | S11: https://www.hdfc.bank.in/credit-cards | T11: Current HDFC PIXEL MITC/product material accessed 2026-09-09 | U11: https://www.hdfc.bank.in/credit-cards/pixel-go-credit-card | V11: Official issuer | W11: 2026-09-09 | X11: Second-pass reward/cashback research; populated only from located source material.
A12: HDFC Bank | B12: Selectable | C12: HDFC Bank UPI RuPay Credit Card | D12: 1% CashPoints on eligible spends. | E12: 3% CashPoints on eligible grocery, supermarket, dining and PayZapp spends; 2% on eligible utility spends. | F12: 1 CashPoint = ₹0.25 for cashback redemption. | G12: Accelerated CashPoints capped at 500 points per category per calendar month. | H12: ₹100 minimum eligible transaction for reward accrual, subject to current terms. | S12: https://www.hdfc.bank.in/credit-cards | T12: Current official catalogue accessed 2026-09-09 | U12: https://www.hdfc.bank.in/credit-cards/hdfc-bank-upi-rupay-credit-card | V12: Official issuer | W12: 2026-09-09 | X12: Second-pass reward/cashback research; populated only from located source material.
A13: HDFC Bank | B13: Selectable | C13: HDFC Bank Regalia Gold Credit Card | D13: 4 Reward Points per ₹150 on eligible retail spends. | E13: Up to 20 Reward Points per ₹150 at selected accelerated partners/SmartBuy offers. | F13: Typical values: up to ₹0.65/point on selected catalogue rewards, about ₹0.50 for eligible flight/hotel redemptions, and about ₹0.20 as statement cashback. | N13: 2% foreign-currency markup, per current official card material. | O13: Up to 12 domestic lounge visits/year; Priority Pass benefit includes up to 6 international lounge visits/year, subject to current programme terms. | P13: ₹5,000 flight voucher at ₹5 lakh annual spend and an additional ₹5,000 flight voucher at ₹7.5 lakh annual spend. | S13: https://www.hdfc.bank.in/credit-cards/regalia-gold-credit-card https://www.hdfc.bank.in/credit-cards | T13: Current official card material accessed 2026-09-09 | U13: https://www.hdfc.bank.in/blogs/regalia-gold-credit-card/redeem-regalia-gold-credit-card-reward-points | V13: Official issuer | W13: 2026-09-09 | X13: Second-pass reward/cashback research; populated only from located source material.
A14: HDFC Bank | B14: Selectable | C14: HDFC Bank Diners Club Privilege Credit Card | D14: Regular Reward Points on eligible spends; card-specific base rate is published on the product page. | E14: 5X rewards on eligible Swiggy and Zomato spends (20 RP/₹150 in the cited card T&C). | G14: Incremental accelerated rewards capped at 2,500 RP/month. | H14: ₹150 for the cited accelerated-reward calculation. | I14: Wallet spends excluded from the cited accelerated offer; merchant/category qualification may use MCC 5411, 5499, 5811, 5812, 5814 or issuer merchant identifiers. | S14: https://www.hdfc.bank.in/credit-cards/diners-club-privilege-credit-card https://www.hdfc.bank.in/credit-cards | T14: Current official product/T&C accessed 2026-09-09
A15: HDFC Bank | B15: Selectable | C15: Tata Neu Plus HDFC Bank Credit Card | D15: 1% NeuCoins on eligible non-Tata spends. | E15: 2% NeuCoins on eligible Tata brand spends plus additional rewards on selected Tata Neu transactions; eligible UPI spends earn up to 1%. | F15: 1 NeuCoin = ₹1 in the Tata Neu ecosystem. | L15: ₹499 + applicable taxes (published HDFC MITC value). | M15: Annual fee waiver at ₹1 lakh eligible annual spend. | S15: https://www.hdfc.bank.in/credit-cards | T15: HDFC MITC updated 2025-07-14; catalogue accessed 2026-09-09 | U15: https://www.hdfc.bank.in/credit-cards/tata-neu-plus-hdfc-bank-credit-card | V15: Official issuer | W15: 2026-09-09 | X15: Second-pass reward/cashback research; populated only from located source material.
A16: HDFC Bank | B16: Selectable | C16: Swiggy HDFC Bank Credit Card | D16: 1% cashback on other eligible spends. | E16: 10% cashback on eligible Swiggy spends and 5% on specified online categories/merchants. | G16: Current issuer page states category-wise statement-cycle caps, including up to ₹1,500 for Swiggy, up to ₹1,500 for the 5% online bucket and up to ₹500 for the 1% bucket. | L16: ₹500 + applicable taxes. | M16: Annual fee waiver at ₹2 lakh eligible annual spend. | S16: https://www.hdfc.bank.in/credit-cards | T16: HDFC MITC updated 2025-07-14; catalogue accessed 2026-09-09 | U16: https://www.hdfc.bank.in/credit-cards/swiggy-hdfc-bank-credit-card | V16: Official issuer | W16: 2026-09-09 | X16: Second-pass reward/cashback research; populated only from located source material.
A17: HDFC Bank | B17: Selectable | C17: Swiggy Ornge HDFC Bank Credit Card | D17: 1% cashback on eligible other spends. | E17: 5% cashback on eligible Swiggy spends and 5% on selected online merchants/categories. | S17: https://www.hdfc.bank.in/credit-cards | T17: Current official catalogue accessed 2026-09-09 | U17: https://www.hdfc.bank.in/credit-cards/swiggy-ornge-hdfc-bank-credit-card | V17: Official issuer | W17: 2026-09-09 | X17: Second-pass reward/cashback research; populated only from located source material.
A18: HDFC Bank | B18: Selectable | C18: Swiggy BLCK HDFC Bank Credit Card | D18: 1% cashback on eligible other spends. | E18: 10% cashback on eligible Swiggy spends and 5% on selected online merchants/categories. | S18: https://www.hdfc.bank.in/credit-cards | T18: Current official catalogue accessed 2026-09-09 | U18: https://www.hdfc.bank.in/credit-cards/swiggy-blck-hdfc-bank-credit-card | V18: Official issuer | W18: 2026-09-09 | X18: Second-pass reward/cashback research; populated only from located source material.
A19: HDFC Bank | B19: Selectable | C19: Marriott Bonvoy HDFC Bank Credit Card | D19: 2 Marriott Bonvoy points per ₹150 on eligible spends. | E19: 8 Marriott Bonvoy points per ₹150 at participating Marriott hotels; 4 points per ₹150 on eligible travel, dining and entertainment categories. | L19: ₹3,000 + applicable taxes. | M19: No annual-fee waiver stated in cited HDFC MITC. | S19: https://www.hdfc.bank.in/credit-cards | T19: HDFC MITC updated 2025-07-14; catalogue accessed 2026-09-09 | U19: https://www.hdfc.bank.in/credit-cards/marriott-bonvoy-credit-card | V19: Official issuer | W19: 2026-09-09 | X19: Second-pass reward/cashback research; populated only from located source material.
A20: HDFC Bank | B20: Selectable | C20: IRCTC HDFC Bank Credit Card | D20: 1 Reward Point per ₹100 on eligible spends. | E20: 5 Reward Points per ₹100 on eligible IRCTC train-ticket spends plus eligible SmartBuy benefits. | F20: 1 Reward Point = ₹1 when used for eligible train-ticket redemption through the specified HDFC/IRCTC channel. | G20: Accelerated IRCTC rewards capped at 1,000 Reward Points/month and 12,000/year under issuer terms. | S20: https://www.hdfc.bank.in/credit-cards | T20: Current official catalogue accessed 2026-09-09 | U20: https://www.hdfc.bank.in/credit-cards/irctc-credit-card | V20: Official issuer | W20: 2026-09-09 | X20: Second-pass reward/cashback research; populated only from located source material.
A21: HDFC Bank | B21: Selectable | C21: HDFC Bank INFINIA Metal Edition Credit Card | D21: 5 Reward Points per ₹150 on eligible retail spends. | E21: Up to 10X Reward Points on eligible SmartBuy spends. | F21: Up to ₹1/point for eligible flight/hotel redemption; airline-mile transfer can be up to 1:1; catalogue about ₹0.50 and cashback about ₹0.30 per point. | S21: https://www.hdfc.bank.in/credit-cards | T21: Current official catalogue accessed 2026-09-09 | U21: https://www.hdfc.bank.in/credit-cards/infinia-credit-card | V21: Official issuer | W21: 2026-09-09 | X21: Second-pass reward/cashback research; populated only from located source material.
A22: ICICI Bank | B22: Selectable | C22: Amazon Pay ICICI Bank Credit Card | D22: 1% cashback on eligible payments outside Amazon/partner acceleration. | E22: 5% cashback on Amazon for eligible Prime members; 3% for eligible non-Prime Amazon purchases; 2% on 100+ eligible Amazon Pay partner merchants; some Amazon digital/gift-card categories earn 2%. | F22: N/A – cashback is credited as Amazon Pay balance/cashback per programme terms. | G22: No general cashback cap stated on the official card page; cashback does not expire under the programme. | I22: No cashback on rent or fuel; specified gold/silver/precious-metal/tax categories and Amazon EMI are excluded under current programme terms. | K22: Nil | L22: Nil | Q22: 1% fuel surcharge waiver subject to issuer terms. | S22: https://www.icicibank.com/personal-banking/cards/credit-card | T22: Current official product/FAQ accessed 2026-09-09
A23: ICICI Bank | B23: Selectable | C23: ICICI Bank Coral Credit Card | D23: 2 Reward Points per ₹100 on eligible retail spends; 1 Reward Point per ₹100 on utilities and insurance. | K23: ₹500 + GST | L23: ₹500 + GST | M23: Annual fee waived on eligible annual spend above ₹1.5 lakh. | O23: Domestic lounge access subject to ₹75,000 spend in the preceding calendar quarter; 1 railway lounge visit/quarter under current programme terms. | Q23: 1% waiver on eligible HPCL transactions of ₹400–₹4,000 at ICICI merchant terminals. | S23: https://www.icicibank.com/personal-banking/cards/credit-card | T23: Current official product material accessed 2026-09-09 | U23: https://www.icici.bank.in/personal-banking/cards/credit-card/coral-credit-card | V23: Official issuer | W23: 2026-09-09 | X23: Second-pass reward/cashback research; populated only from located source material.
A24: ICICI Bank | B24: Selectable | C24: ICICI Bank Sapphiro Credit Card | D24: 2 Reward Points per ₹100 on eligible domestic spends and 4 per ₹100 on eligible international spends; 1 per ₹100 on utilities/insurance. | K24: ₹6,500 + GST | L24: ₹3,500 + GST | M24: Annual fee waived on eligible annual spend above ₹6 lakh. | O24: Domestic lounge access subject to ₹75,000 previous-quarter spend; current card material also provides international lounge access. Duo variants may carry separate network entitlements. | R24: Golf entitlement linked to previous-month spend under current programme. | S24: https://www.icicibank.com/personal-banking/cards/credit-card | T24: Current official product material accessed 2026-09-09 | U24: https://www.icici.bank.in/personal-banking/cards/credit-card | V24: Official issuer | W24: 2026-09-09 | X24: Second-pass reward/cashback research; populated only from located source material.
A25: ICICI Bank | B25: Selectable | C25: Times Black ICICI Bank Credit Card | D25: Reward earn equivalent to about 2% on eligible domestic spends and 2.5% on eligible international spends. | E25: Up to 6X on eligible flight/voucher bookings and up to 12X on hotels through eligible iShop channels. | F25: 1 Reward Point can be worth up to ₹1 on selected products/vouchers; statement cashback value is lower (about ₹0.40/point). | N25: 1.49% | S25: https://www.icicibank.com/personal-banking/cards/credit-card | T25: Current official product material accessed 2026-09-09 | U25: https://www.icici.bank.in/personal-banking/cards/credit-card/times-black-icici-credit-card | V25: Official issuer | W25: 2026-09-09 | X25: Second-pass reward/cashback research; populated only from located source material.
A26: ICICI Bank | B26: Selectable | C26: ICICI Bank Emeralde Credit Card | D26: 4 Reward Points per ₹100 on eligible domestic and international retail spends; lower earn on utilities/insurance. | Q26: 1% fuel surcharge waiver on eligible fuel transactions up to ₹4,000, subject to current terms. | S26: https://www.icicibank.com/personal-banking/cards/credit-card | T26: Current official product material accessed 2026-09-09 | U26: https://www.icici.bank.in/personal-banking/cards/credit-card | V26: Official issuer | W26: 2026-09-09 | X26: Second-pass reward/cashback research; populated only from located source material.
A27: ICICI Bank | B27: Selectable | C27: ICICI Bank Rubyx Credit Card | D27: 2 Reward Points per ₹100 on eligible domestic spends and 4 per ₹100 on eligible international spends; 1 per ₹100 on utilities/insurance. | S27: https://www.icicibank.com/personal-banking/cards/credit-card | T27: Current official catalogue accessed 2026-09-09 | U27: https://www.icici.bank.in/personal-banking/cards/credit-card | V27: Official issuer | W27: 2026-09-09 | X27: Second-pass reward/cashback research; populated only from located source material.
A28: ICICI Bank | B28: Selectable | C28: ICICI Bank Platinum Chip Credit Card | D28: 2 Reward Points per ₹100 on eligible retail spends; 1 Reward Point per ₹100 on utilities and insurance. | K28: Nil | L28: Nil | Q28: Fuel-surcharge waiver available subject to current ICICI terms. | S28: https://www.icicibank.com/personal-banking/cards/credit-card | T28: Current official product page accessed 2026-09-09 | U28: https://www.icici.bank.in/personal-banking/cards/credit-card/platinum-chip-credit-card | V28: Official issuer | W28: 2026-09-09 | X28: Second-pass reward/cashback research; populated only from located source material.
A29: ICICI Bank | B29: Selectable | C29: Adani One ICICI Bank Signature Credit Card | D29: 1.5% Adani Reward Points/value on eligible domestic spends and 2% on eligible international spends. | E29: Up to 7% reward value on eligible Adani One ecosystem spends. | K29: ₹5,000 + GST | L29: ₹5,000 + GST | O29: Airport/co-brand benefits include lounge/airport-service entitlements as published for the card. | P29: Welcome flight voucher benefit linked to fee payment and ₹25,000 eligible spend within 60 days, subject to current terms. | R29: Includes Adani airport services such as Pranaam/Porter/parking entitlements under current programme terms. | S29: https://www.icicibank.com/personal-banking/cards/credit-card | T29: Current official co-brand page accessed 2026-09-09 | U29: https://www.icici.bank.in/personal-banking/cards/credit-card/adani-icici-credit-card/signature-credit-card | V29: Official issuer | W29: 2026-09-09 | X29: Second-pass reward/cashback research; populated only from located source material.
A30: ICICI Bank | B30: Selectable | C30: Adani One ICICI Bank Platinum Credit Card | D30: 1% Adani Reward Points/value on eligible domestic spends and 1.5% on eligible international spends. | E30: Up to 3% reward value on eligible Adani One ecosystem spends. | K30: ₹750 + GST | L30: ₹750 + GST | R30: Current official co-brand material includes domestic lounge and Adani airport-service benefits such as Porter/premium parking. | S30: https://www.icicibank.com/personal-banking/cards/credit-card | T30: Current official co-brand page accessed 2026-09-09 | U30: https://www.icici.bank.in/personal-banking/cards/credit-card/adani-icici-credit-card/platinum-credit-card | V30: Official issuer | W30: 2026-09-09 | X30: Second-pass reward/cashback research; populated only from located source material.
A31: ICICI Bank | B31: Selectable | C31: MakeMyTrip ICICI Bank Credit Card | E31: Up to 6% myCash on eligible MakeMyTrip transactions, subject to category/booking terms. | N31: 0.99% | O31: Official card material advertises 8 domestic and 1 international lounge visit/year, subject to conditions. | R31: MakeMyTrip joining/annual-voucher benefits and MMTBLACK Gold-related travel benefits under current terms. | S31: https://www.icicibank.com/personal-banking/cards/credit-card | T31: Current official product page accessed 2026-09-09
A32: ICICI Bank | B32: Selectable | C32: Emirates ICICI Bank Emeralde Credit Card | D32: 2 Emirates Skywards Miles per ₹100 on eligible domestic and international spends. | S32: https://www.icicibank.com/personal-banking/cards/credit-card | T32: Current official catalogue accessed 2026-09-09 | U32: https://www.icici.bank.in/personal-banking/cards/credit-card/emirates-skywards/emirates-emeralde | V32: Official issuer | W32: 2026-09-09 | X32: Second-pass reward/cashback research; populated only from located source material.
A33: ICICI Bank | B33: Selectable | C33: Emirates ICICI Bank Sapphiro Credit Card | D33: 1.5 Emirates Skywards Miles per ₹100 on eligible spends. | S33: https://www.icicibank.com/personal-banking/cards/credit-card | T33: Current official catalogue accessed 2026-09-09 | U33: https://www.icici.bank.in/personal-banking/cards/credit-card | V33: Official issuer | W33: 2026-09-09 | X33: Second-pass reward/cashback research; populated only from located source material.
A34: ICICI Bank | B34: Selectable | C34: HPCL Super Saver ICICI Bank Credit Card | E34: 5% value proposition on selected categories; 20 RP/₹100 on eligible accelerated spends, with published category caps. | G34: Accelerated reward value capped at ₹100/month for specified categories; HPCL cashback component capped at ₹200/month under current programme. | K34: ₹500 + GST | L34: ₹500 + GST | Q34: Up to 5% fuel savings proposition: 4% cashback component (cap applies) plus 1% surcharge waiver; additional HP Pay benefits may apply. | S34: https://www.icicibank.com/personal-banking/cards/credit-card | T34: Current official card page accessed 2026-09-09
A35: ICICI Bank | B35: Selectable | C35: HPCL ICICI Bank Coral Credit Card | D35: 2 Reward Points per ₹100 on eligible retail spends; 1 per ₹100 on utilities/insurance. | E35: 2.5% cashback/value back on eligible HPCL fuel spends, subject to monthly cap and conditions. | G35: HPCL fuel cashback/value-back cap commonly stated as ₹100/month on the issuer product proposition. | K35: ₹199 + GST | L35: ₹199 + GST | Q35: HPCL value proposition includes 2.5% cashback (max ₹100/month) plus 1% fuel surcharge waiver on eligible ICICI POS transactions. | R35: BookMyShow discount published for this card, subject to monthly/transaction limits. | S35: https://www.icicibank.com/personal-banking/cards/credit-card | T35: Current official card page accessed 2026-09-09 | U35: https://www.icici.bank.in/personal-banking/cards/credit-card/hpcl-coral-credit-card | V35: Official issuer | W35: 2026-09-09 | X35: Second-pass reward/cashback research; populated only from located source material.
A36: ICICI Bank | B36: Selectable | C36: ICICI Bank Expressions Credit Card | D36: 3 Reward Points per ₹100 on eligible general retail spends; 1 per ₹100 on utilities/insurance. | S36: https://www.icicibank.com/personal-banking/cards/credit-card | T36: Current official catalogue accessed 2026-09-09 | U36: https://www.icici.bank.in/personal-banking/cards/credit-card/expressions-card | V36: Official issuer | W36: 2026-09-09 | X36: Second-pass reward/cashback research; populated only from located source material.
A37: ICICI Bank | B37: Selectable | C37: ICICI Bank Emeralde Private Metal Credit Card | D37: 6 Reward Points per ₹200 on eligible retail spends. | K37: ₹12,499 + GST | L37: ₹12,499 + GST | O37: Unlimited domestic and international lounge access under current programme terms. | Q37: 1% fuel surcharge waiver on eligible fuel transactions up to ₹4,000. | R37: Premium Taj/EazyDiner/golf benefits under current card programme. | S37: https://www.icicibank.com/personal-banking/cards/credit-card | T37: Current official product page accessed 2026-09-09 | U37: https://www.icici.bank.in/personal-banking/cards/credit-card/emeralde-private-metal-credit-card | V37: Official issuer | W37: 2026-09-09 | X37: Second-pass reward/cashback research; populated only from located source material.
A38: ICICI Bank | B38: Discontinued | C38: Emirates Skywards ICICI Bank Rubyx Credit Card | D38: 1 Emirates Skywards Mile per ₹100 on eligible spends under the legacy card proposition. | L38: Published as non-waivable in legacy official material. | S38: https://www.icicibank.com/personal-banking/cards/credit-card | T38: Legacy official product material; discontinued | U38: https://www.icici.bank.in/personal-banking/cards/credit-card | V38: Official issuer | W38: 2026-09-09 | X38: Discontinued card; earn rate recovered from issuer legacy/product material.
A39: ICICI Bank | B39: Discontinued | C39: MakeMyTrip ICICI Bank Signature Credit Card | D39: 1.25 MyCash per ₹200 on eligible domestic spends outside MakeMyTrip; 1.5 MyCash per ₹200 on eligible international spends. | E39: 2 MyCash per ₹200 on eligible MakeMyTrip flight bookings and 4 MyCash per ₹200 on eligible MakeMyTrip hotel/holiday bookings. | F39: 1 MyCash = ₹1 when redeemed under the MakeMyTrip programme, subject to programme rules. | S39: https://www.icicibank.com/personal-banking/cards/credit-card | T39: Legacy official product material; discontinued | U39: https://www.icici.bank.in/personal-banking/cards/credit-card | V39: Official issuer | W39: 2026-09-09 | X39: Discontinued legacy MakeMyTrip variant; rates recovered from issuer legacy terms.
A40: ICICI Bank | B40: Discontinued | C40: MakeMyTrip ICICI Bank Platinum Credit Card | D40: 1 MyCash per ₹200 on eligible domestic spends outside MakeMyTrip; 1.25 MyCash per ₹200 on eligible international spends. | E40: 2 MyCash per ₹200 on eligible MakeMyTrip flight bookings and 3 MyCash per ₹200 on eligible MakeMyTrip hotel/holiday bookings. | F40: 1 MyCash = ₹1 under the MakeMyTrip programme, subject to programme rules. | S40: https://www.icicibank.com/personal-banking/cards/credit-card | T40: Legacy official product material; discontinued | U40: https://www.icici.bank.in/personal-banking/cards/credit-card/makemytrip/platinum-credit-card/tnc-for-governing-mmt-platinum-credit-card | V40: Official issuer | W40: 2026-09-09 | X40: Second-pass reward/cashback research; populated only from located source material.
A41: ICICI Bank | B41: Discontinued | C41: Chennai Super Kings ICICI Bank Credit Card | E41: Legacy programme: 10 RP/₹100 on eligible CSK match-day spends; fuel excluded. | K41: ₹500 + GST (legacy official terms). | M41: Legacy annual fee waiver above ₹1.5 lakh eligible spend in previous year. | P41: Legacy joining/renewal benefit of 2,000 reward points where fee conditions were met. | S41: https://www.icicibank.com/personal-banking/cards/credit-card | T41: Legacy official product material; discontinued
A42: ICICI Bank | B42: Discontinued | C42: ICICI Bank Parakram Select Credit Card | D42: Legacy programme included 2 RP/₹100 on specified eligible spends. | E42: Legacy programme included 10 RP/₹100 on grocery/departmental/CSD categories. | G42: Legacy accelerated category cap: 1,000 RP/month. | Q42: Legacy 1% fuel surcharge waiver on eligible fuel transactions up to ₹4,000. | S42: https://www.icicibank.com/personal-banking/cards/credit-card | T42: Legacy official product material; discontinued
A43: ICICI Bank | B43: Discontinued | C43: ICICI Bank Parakram Credit Card | D43: 1 Reward Point per ₹100 on eligible spends. | E43: 5 Reward Points per ₹100 on eligible grocery, departmental-store and CSD spends. | G43: Accelerated category rewards capped at 1,000 Reward Points/month under legacy issuer terms. | U43: https://www.icici.bank.in/personal-banking/cards/credit-card/parakram-cards/parakram | V43: Official issuer | W43: 2026-09-09 | X43: Discontinued; issuer legacy page retained.
A44: Axis Bank | B44: Selectable | C44: Axis Bank SELECT Credit Card | D44: 10 EDGE REWARD Points per ₹200 on eligible spends. | E44: 2X points on eligible retail-shopping categories, subject to programme caps. | Q44: 1% fuel surcharge waiver subject to card-specific eligible transaction range/cap in current Axis KFS. | S44: https://www.axisbank.com/docs/default-source/default-document-library/sosc-credit-cards.pdf | T44: Current Axis KFS accessed 2026-09-09 | U44: https://www.axis.bank.in/cards/credit-card/axis-bank-select-credit-card | V44: Official issuer | W44: 2026-09-09 | X44: Second-pass reward/cashback research; populated only from located source material.
A45: Axis Bank | B45: Selectable | C45: IndianOil Axis Bank Credit Card | D45: 1 EDGE REWARD Point per ₹100 on eligible spends. | E45: 20 EDGE REWARD Points per ₹100 on eligible IndianOil fuel spends (4% value back) and 5 points per ₹100 on eligible online spends. | G45: Accelerated earning applies up to the issuer-defined monthly eligible-spend thresholds (including ₹5,000/month for key accelerated buckets). | Q45: 1% fuel surcharge waiver subject to card-specific eligible transaction range/cap in current Axis KFS. | S45: https://www.axisbank.com/docs/default-source/default-document-library/sosc-credit-cards.pdf | T45: Current Axis KFS accessed 2026-09-09 | U45: https://www.axis.bank.in/cards/credit-card/indianoil-axis-bank-credit-card | V45: Official issuer | W45: 2026-09-09 | X45: Second-pass reward/cashback research; populated only from located source material.
A46: Axis Bank | B46: Selectable | C46: Airtel Axis Bank Credit Card | D46: 1% cashback on other eligible spends. | E46: 25% cashback on eligible Airtel mobile/broadband/Wi-Fi/DTH payments via Airtel Thanks; 10% on eligible utilities through Airtel Thanks; 10% on specified partner merchants including Zomato/Blinkit/District Movies. | G46: Current 2026 terms use dynamic caps linked to base cashback earned in the statement for Airtel and utilities; partner-category caps also apply. | Q46: 1% fuel surcharge waiver subject to card-specific eligible transaction range/cap in current Axis KFS. | S46: https://www.axisbank.com/docs/default-source/default-document-library/sosc-credit-cards.pdf | T46: Current Axis KFS accessed 2026-09-09 | U46: https://www.axis.bank.in/cards/credit-card/airtel-axis-bank-credit-card | V46: Official issuer | W46: 2026-09-09 | X46: Current proposition checked against 2026 issuer terms; avoid older fixed-cap summaries.
A47: Axis Bank | B47: Selectable | C47: Flipkart Axis Bank Credit Card | D47: 1% cashback on eligible other spends. | E47: 5% cashback on eligible Flipkart and Cleartrip spends; 7.5% on eligible Myntra spends and 4% at selected preferred merchants under the current proposition, subject to caps. | Q47: 1% fuel surcharge waiver subject to card-specific eligible transaction range/cap in current Axis KFS. | S47: https://www.axisbank.com/docs/default-source/default-document-library/sosc-credit-cards.pdf | T47: Current Axis KFS accessed 2026-09-09 | U47: https://www.axis.bank.in/cards/credit-card | V47: Official issuer | W47: 2026-09-09 | X47: Second-pass reward/cashback research; populated only from located source material.
A48: Axis Bank | B48: Selectable | C48: Axis Bank Privilege Credit Card | D48: 10 EDGE REWARD Points per ₹200 on eligible spends. | Q48: 1% fuel surcharge waiver subject to card-specific eligible transaction range/cap in current Axis KFS. | S48: https://www.axisbank.com/docs/default-source/default-document-library/sosc-credit-cards.pdf | T48: Current Axis KFS accessed 2026-09-09 | U48: https://www.axis.bank.in/cards/credit-card | V48: Official issuer | W48: 2026-09-09 | X48: Second-pass reward/cashback research; populated only from located source material.
A49: Axis Bank | B49: Selectable | C49: Axis Bank Neo Credit Card | D49: 1 EDGE REWARD Point per ₹200 on eligible spends. | E49: Card value is primarily delivered through recurring merchant discounts/offers rather than a high accelerated base earn. | S49: https://www.axisbank.com/docs/default-source/default-document-library/sosc-credit-cards.pdf | T49: Current official schedule/KFS accessed 2026-09-09 | U49: https://www.axis.bank.in/cards/credit-card | V49: Official issuer | W49: 2026-09-09 | X49: Second-pass reward/cashback research; populated only from located source material.
A50: Axis Bank | B50: Selectable | C50: IndiGo Axis Bank Premium Credit Card | D50: 2 IndiGo BluChips per ₹100 on eligible spends. | E50: 7 BluChips per ₹100 on eligible IndiGo spends. | S50: https://www.axisbank.com/docs/default-source/default-document-library/sosc-credit-cards.pdf | T50: Current official schedule/KFS accessed 2026-09-09 | U50: https://www.axis.bank.in/cards/credit-card | V50: Official issuer | W50: 2026-09-09 | X50: Second-pass reward/cashback research; populated only from located source material.
A51: Axis Bank | B51: Selectable | C51: Axis Bank MY ZONE Credit Card | D51: 4 EDGE REWARD Points per ₹200 on eligible spends. | Q51: 1% fuel surcharge waiver subject to card-specific eligible transaction range/cap in current Axis KFS. | S51: https://www.axisbank.com/docs/default-source/default-document-library/sosc-credit-cards.pdf | T51: Current Axis KFS accessed 2026-09-09 | U51: https://www.axis.bank.in/cards/credit-card | V51: Official issuer | W51: 2026-09-09 | X51: Second-pass reward/cashback research; populated only from located source material.
A52: Axis Bank | B52: Selectable | C52: Axis Bank ACE Credit Card | D52: 1.5% cashback on eligible other spends. | E52: 5% cashback on eligible utility bill payments/DTH/mobile recharges through Google Pay; 4% on eligible Swiggy, Zomato and Ola spends. | Q52: 1% fuel surcharge waiver subject to card-specific eligible transaction range/cap in current Axis KFS. | S52: https://www.axisbank.com/docs/default-source/default-document-library/sosc-credit-cards.pdf | T52: Current Axis KFS accessed 2026-09-09 | U52: https://www.axis.bank.in/cards/credit-card/axis-bank-ace-credit-card | V52: Official issuer | W52: 2026-09-09 | X52: Second-pass reward/cashback research; populated only from located source material.
A53: Axis Bank | B53: Selectable | C53: Axis Bank Rewards Credit Card | D53: 2 EDGE REWARD Points per ₹125 on eligible spends. | E53: 10X total earn (20 EDGE REWARD Points per ₹125) on eligible apparel and departmental-store spends. | F53: 1 EDGE REWARD Point = ₹0.20 on the issuer value chart. | G53: Incremental 9X component capped at 1,008 points per statement month, corresponding to ₹7,000 accelerated-category spend. | Q53: 1% waiver on eligible fuel transactions ₹400–₹5,000; current KFS cap applies. | S53: https://www.axisbank.com/docs/default-source/default-document-library/sosc-credit-cards.pdf | T53: Current Axis KFS accessed 2026-09-09 | U53: https://www.axis.bank.in/cards/credit-card/rewards-credit-card | V53: Official issuer | W53: 2026-09-09 | X53: Second-pass reward/cashback research; populated only from located source material.
A54: Axis Bank | B54: Selectable | C54: Google Pay Flex Axis Bank Credit Card | D54: Earn Stars on eligible cumulative spend; current structure awards Stars against spend milestones rather than a simple fixed cashback rate. | E54: Category/merchant multipliers apply in Google Pay/Flex campaigns. | F54: 1 Star is represented as ₹1 of eligible reward value in the programme. | S54: https://www.axisbank.com/docs/default-source/default-document-library/sosc-credit-cards.pdf | T54: Current official schedule/KFS accessed 2026-09-09 | U54: https://www.axis.bank.in/cards/credit-card | V54: Official issuer | W54: 2026-09-09 | X54: Second-pass reward/cashback research; populated only from located source material.
A55: Axis Bank | B55: Selectable | C55: Axis Bank HORIZON Credit Card | D55: 2 EDGE Miles per ₹100 on eligible spends. | E55: 5 EDGE Miles per ₹100 on eligible Travel EDGE/direct airline/hotel spends. | Q55: 1% waiver on eligible fuel transactions ₹400–₹5,000; current KFS cap applies. | S55: https://www.axisbank.com/docs/default-source/default-document-library/sosc-credit-cards.pdf | T55: Current Axis KFS accessed 2026-09-09 | U55: https://www.axis.bank.in/cards/credit-card | V55: Official issuer | W55: 2026-09-09 | X55: Second-pass reward/cashback research; populated only from located source material.
A56: Axis Bank | B56: Selectable | C56: Axis Bank Cashback Credit Card | D56: 0.75% cashback on eligible offline/POS and travel spends. | E56: Eligible online spend: 2% on first ₹5,000; 5% on ₹5,001–₹40,000; 7% thereafter, subject to current T&C. | F56: N/A – statement cashback. | G56: Accelerated cashback capped at ₹4,000/statement cycle; utility cashback capped at ₹100/statement cycle. | I56: Transportation/tolls 4111, 4121, 4131, 4784; insurance 6300, 6381, 5960, 6012, 6051; education 8211, 8241, 8244, 8249, 8299; jewellery/precious metals 5944, 5094; government 9211, 9222, 9311, 9399, 9402, 9405, 8220; wallet 6540; rent 6513; fuel 5541, 5542, 5983. | K56: ₹1,000 + GST | L56: ₹1,000 + GST | M56: Waived at ₹4 lakh eligible annual retail spend; rent MCC 6513 and wallet MCC 6540 excluded from waiver spend. | P56: Welcome 5,000 EDGE Reward Points (stated value ₹1,000) after first spend within 30 days, subject to joining-fee conditions. | R56: 0.5% utility cashback on MCC 4816/4899/4900, capped at ₹100/statement. | S56: https://www.axisbank.com/docs/default-source/ld/axis-bank-cashback-credit-card-tnc.pdf https://www.axisbank.com/docs/default-source/default-document-library/sosc-credit-cards.pdf | T56: Current official T&C/KFS accessed 2026-09-09
A57: Axis Bank | B57: Selectable | C57: Axis Bank Magnus Credit Card | D57: 12 EDGE REWARD Points per ₹200 on eligible monthly spends up to the current threshold; higher earn applies above the specified monthly spend threshold. | E57: Up to 5X on eligible Travel EDGE spends. | K57: ₹12,500 + GST | L57: ₹12,500 + GST | S57: https://www.axisbank.com/docs/default-source/default-document-library/sosc-credit-cards.pdf | T57: Current Axis MITC/KFS accessed 2026-09-09 | U57: https://www.axis.bank.in/cards/credit-card | V57: Official issuer | W57: 2026-09-09 | X57: Second-pass reward/cashback research; populated only from located source material.
A58: Axis Bank | B58: Selectable | C58: Axis Bank Reserve Credit Card | D58: 15 EDGE REWARD Points per ₹200 on eligible spends. | E58: 2X points on eligible international spends. | S58: https://www.axisbank.com/docs/default-source/default-document-library/sosc-credit-cards.pdf | T58: Current official schedule/KFS accessed 2026-09-09 | U58: https://www.axis.bank.in/cards/credit-card | V58: Official issuer | W58: 2026-09-09 | X58: Second-pass reward/cashback research; populated only from located source material.
A59: Axis Bank | B59: Selectable | C59: Axis Bank MY ZONE Easy Credit Card | D59: 4 EDGE REWARD Points per ₹200 on eligible spends. | E59: Additional value is largely merchant/movie-offer based. | S59: https://www.axisbank.com/docs/default-source/default-document-library/sosc-credit-cards.pdf | T59: Current official schedule/KFS accessed 2026-09-09 | U59: https://www.axis.bank.in/cards/credit-card | V59: Official issuer | W59: 2026-09-09 | X59: Second-pass reward/cashback research; populated only from located source material.
A60: Axis Bank | B60: Selectable | C60: IndianOil Axis Bank Easy Credit Card | D60: 1 EDGE REWARD Point per ₹100 on eligible spends. | E60: 20 EDGE REWARD Points per ₹100 on eligible IndianOil fuel spends and 5 per ₹100 on eligible online spends under the legacy/easy proposition. | S60: https://www.axisbank.com/docs/default-source/default-document-library/sosc-credit-cards.pdf | T60: Current official schedule/KFS accessed 2026-09-09 | U60: https://coffer.gold/cards/indianoil-easy-axis-bank-credit-card | V60: Credible secondary | W60: 2026-09-09 | X60: Exact legacy Axis product page was not reliably surfaced; rate cross-checked against card databases and Axis programme references.
A61: Axis Bank | B61: Selectable | C61: Axis Bank Privilege Easy Credit Card | D61: 10 EDGE REWARD Points per ₹200 on eligible spends under the legacy/easy proposition. | S61: https://www.axisbank.com/docs/default-source/default-document-library/sosc-credit-cards.pdf | T61: Current official schedule/KFS accessed 2026-09-09 | U61: https://www.paisabazaar.com/axis-bank/privilege-easy-credit-card/ | V61: Credible secondary | W61: 2026-09-09 | X61: Legacy product; issuer page was not readily accessible in current catalogue.
A62: Axis Bank | B62: Selectable | C62: Axis Bank Atlas Credit Card | D62: 2 EDGE Miles per ₹100 on eligible spends. | E62: 5 EDGE Miles per ₹100 on eligible travel-category spends as defined by Axis. | S62: https://www.axisbank.com/docs/default-source/default-document-library/sosc-credit-cards.pdf | T62: Current official schedule/KFS accessed 2026-09-09 | U62: https://www.axis.bank.in/cards/credit-card | V62: Official issuer | W62: 2026-09-09 | X62: Second-pass reward/cashback research; populated only from located source material.
A63: Axis Bank | B63: Selectable | C63: Axis Bank AURA Credit Card | D63: 2 EDGE REWARD Points per ₹200 on eligible spends. | E63: 5X rewards on eligible insurance spends, subject to transaction/programme limits. | Q63: 1% fuel surcharge waiver subject to current KFS; published cap ₹250/statement cycle. | S63: https://www.axisbank.com/docs/default-source/default-document-library/sosc-credit-cards.pdf | T63: Current Axis KFS accessed 2026-09-09 | U63: https://www.axis.bank.in/cards/credit-card/axis-bank-aura-credit-card | V63: Official issuer | W63: 2026-09-09 | X63: Second-pass reward/cashback research; populated only from located source material.
A64: Axis Bank | B64: Selectable | C64: IndianOil Axis Bank Premium Credit Card | D64: 1 EDGE Mile per ₹150 on eligible other spends. | E64: 6X earn on eligible IndianOil fuel spends and 2X on eligible grocery/supermarket spends. | F64: Issuer proposition values 1 EDGE Mile at approximately ₹1 for specified redemption/transfer routes, subject to programme terms. | S64: https://www.axisbank.com/docs/default-source/default-document-library/sosc-credit-cards.pdf | T64: Current official schedule/KFS accessed 2026-09-09 | U64: https://www.axis.bank.in/cards/credit-card | V64: Official issuer | W64: 2026-09-09 | X64: Second-pass reward/cashback research; populated only from located source material.
A65: Axis Bank | B65: Selectable | C65: Axis Bank Pride Platinum Credit Card | D65: 4 EDGE REWARD Points per ₹200 on eligible spends. | Q65: 1% fuel surcharge waiver subject to current KFS; published cap ₹250/statement cycle. | S65: https://www.axisbank.com/docs/default-source/default-document-library/sosc-credit-cards.pdf | T65: Current Axis KFS accessed 2026-09-09 | U65: https://www.axis.bank.in/cards/credit-card | V65: Official issuer | W65: 2026-09-09 | X65: Second-pass reward/cashback research; populated only from located source material.
A66: Axis Bank | B66: Selectable | C66: Axis Bank Pride Signature Credit Card | D66: 8 EDGE REWARD Points per ₹200 on eligible spends. | S66: https://www.axisbank.com/docs/default-source/default-document-library/sosc-credit-cards.pdf | T66: Current official schedule/KFS accessed 2026-09-09 | U66: https://www.axis.bank.in/cards/credit-card | V66: Official issuer | W66: 2026-09-09 | X66: Second-pass reward/cashback research; populated only from located source material.
A67: Axis Bank | B67: Selectable | C67: SpiceJet Axis Bank Voyage Black Credit Card | D67: 6 SpiceClub Points per ₹200 on eligible other domestic retail/international spends. | E67: 12 SpiceClub Points per ₹200 on eligible online food, bill-payment and entertainment spends; up to 28 points per ₹200 on SpiceJet when combined with Gold-tier membership earn. | S67: https://www.axisbank.com/docs/default-source/default-document-library/sosc-credit-cards.pdf | T67: Current official schedule/KFS accessed 2026-09-09 | U67: https://www.axis.bank.in/cards/credit-card/spicejet-axis-bank-voyage-black-credit-card | V67: Official issuer | W67: 2026-09-09 | X67: Second-pass reward/cashback research; populated only from located source material.
A68: Axis Bank | B68: Selectable | C68: Fibe Axis Bank Credit Card | D68: 1% cashback on eligible other spends. | E68: 3% cashback on eligible food, entertainment and local-commute categories. | G68: Accelerated cashback capped at about ₹1,500 per statement cycle under the card proposition. | S68: https://www.axisbank.com/docs/default-source/default-document-library/sosc-credit-cards.pdf | T68: Current official schedule/KFS accessed 2026-09-09 | U68: https://www.axis.bank.in/cards/credit-card | V68: Official issuer | W68: 2026-09-09 | X68: Second-pass reward/cashback research; populated only from located source material.
A69: Axis Bank | B69: Selectable | C69: Shoppers Stop Axis Bank Credit Card | D69: 2 First Citizen Points per ₹200 on eligible spends outside Shoppers Stop. | E69: Accelerated First Citizen earn at Shoppers Stop, including higher earn on private labels/beauty categories under the current proposition. | S69: https://www.axisbank.com/docs/default-source/default-document-library/sosc-credit-cards.pdf | T69: Current official schedule/KFS accessed 2026-09-09 | U69: https://www.axis.bank.in/cards/credit-card | V69: Official issuer | W69: 2026-09-09 | X69: Second-pass reward/cashback research; populated only from located source material.
A70: Axis Bank | B70: Selectable | C70: SpiceJet Axis Bank Voyage Credit Card | D70: 3 SpiceClub Points per ₹200 on eligible other qualifying spends. | E70: 6 SpiceClub Points per ₹200 on eligible online utility/food/entertainment spends; up to 18 points per ₹200 on SpiceJet when combined with Silver-tier membership earn. | S70: https://www.axisbank.com/docs/default-source/default-document-library/sosc-credit-cards.pdf | T70: Current official schedule/KFS accessed 2026-09-09 | U70: https://www.axis.bank.in/cards/credit-card/spicejet-axis-bank-voyage-credit-card | V70: Official issuer | W70: 2026-09-09 | X70: Second-pass reward/cashback research; populated only from located source material.
A71: Axis Bank | B71: Selectable | C71: Samsung Axis Bank Signature Credit Card | D71: 5 EDGE REWARD Points per ₹100 on eligible other spends. | E71: 10 EDGE REWARD Points per ₹100 at selected accelerated partners plus 10% cashback on eligible Samsung purchases, subject to caps. | Q71: 1% fuel surcharge waiver subject to card-specific eligible transaction range/cap in current Axis KFS. | S71: https://www.axisbank.com/docs/default-source/default-document-library/sosc-credit-cards.pdf | T71: Current Axis KFS accessed 2026-09-09 | U71: https://www.axis.bank.in/cards/credit-card | V71: Official issuer | W71: 2026-09-09 | X71: Second-pass reward/cashback research; populated only from located source material.
A72: Axis Bank | B72: Selectable | C72: Miles & More Axis Bank Credit Card | D72: World Select variant: 6 Miles & More award miles per ₹200 eligible spend; World variant: 4 miles per ₹200. | S72: https://www.axisbank.com/docs/default-source/default-document-library/sosc-credit-cards.pdf | T72: Current official schedule/KFS accessed 2026-09-09 | U72: https://www.axis.bank.in/cards/credit-card/miles-more-credit-card | V72: Official issuer | W72: 2026-09-09 | X72: Catalogue name spans World Select and World variants; rates are network/product-variant dependent.
A73: Axis Bank | B73: Selectable | C73: LIC Axis Bank Signature Credit Card | D73: 1 Reward Point per ₹100 on eligible other transactions. | E73: 2 Reward Points per ₹100 on eligible LIC premium payments and foreign-currency transactions. | S73: https://www.axisbank.com/docs/default-source/default-document-library/sosc-credit-cards.pdf | T73: Current official schedule/KFS accessed 2026-09-09 | U73: https://www.axis.bank.in/cards/credit-card/lic-axis-bank-signature-credit-card | V73: Official issuer | W73: 2026-09-09 | X73: Second-pass reward/cashback research; populated only from located source material.
A74: Axis Bank | B74: Selectable | C74: LIC Axis Bank Platinum Credit Card | D74: 1 Reward Point per ₹100 on eligible other transactions. | E74: 2 Reward Points per ₹100 on eligible LIC premium payments and foreign-currency transactions. | S74: https://www.axisbank.com/docs/default-source/default-document-library/sosc-credit-cards.pdf | T74: Current official schedule/KFS accessed 2026-09-09 | U74: https://www.axis.bank.in/cards/credit-card | V74: Official issuer | W74: 2026-09-09 | X74: Second-pass reward/cashback research; populated only from located source material.
A75: Axis Bank | B75: Discontinued | C75: Flipkart Axis Bank Super Elite Credit Card | D75: 2 SuperCoins per ₹100 on eligible spends outside Flipkart. | E75: On Flipkart: additional 6 SuperCoins/₹100 for non-Plus customers and 12/₹100 for Plus customers, on top of Flipkart loyalty earn; issuer page describes total earning up to 8 or 16 SuperCoins/₹100 respectively. | G75: Flipkart transaction-level SuperCoin caps apply; outside-Flipkart 2 SuperCoins/₹100 is described as uncapped. | S75: https://www.axisbank.com/docs/default-source/default-document-library/sosc-credit-cards.pdf | T75: Legacy/current Axis issuer terms accessed 2026-09-09; card discontinued | U75: https://www.axis.bank.in/cards/credit-card/flipkart-axis-bank-super-elite-credit-card | V75: Official issuer | W75: 2026-09-09 | X75: Discontinued for new applications; legacy Axis product page remains live.
A76: Axis Bank | B76: Discontinued | C76: Samsung Axis Bank Infinite Credit Card | D76: 5 EDGE REWARD Points per ₹100 on eligible domestic spends. | E76: 15 EDGE REWARD Points per ₹100 at selected partners/international categories plus 10% cashback on eligible Samsung purchases. | S76: https://www.axisbank.com/docs/default-source/default-document-library/sosc-credit-cards.pdf | T76: Legacy/current Axis issuer terms accessed 2026-09-09; card discontinued | U76: https://www.axis.bank.in/cards/credit-card/samsung-axis-bank-infinite-credit-card | V76: Official issuer | W76: 2026-09-09 | X76: No longer accepting applications; issuer legacy page remains live.
A77: Axis Bank | B77: Discontinued | C77: Freecharge Axis Bank Credit Card | D77: 1 EDGE REWARD Point on the issuer-defined eligible spend unit under the legacy proposition. | E77: Monthly milestone rewards: 100 points for ₹2,000-₹4,999 eligible monthly spend; total 350 points at ₹5,000+ eligible monthly spend. | S77: https://www.axisbank.com/docs/default-source/default-document-library/sosc-credit-cards.pdf | T77: Legacy/current Axis issuer terms accessed 2026-09-09; card discontinued | U77: https://www.axis.bank.in/cards/credit-card/axis-bank-freecharge-credit-card | V77: Official issuer | W77: 2026-09-09 | X77: Legacy card page does not clearly expose the spend denominator beside the base 1-point statement; milestone schedule is explicit.
A78: Axis Bank | B78: Discontinued | C78: Freecharge Plus Axis Bank Credit Card | D78: 1% cashback on eligible other spends. | E78: 5% cashback on eligible Freecharge spends and 2% on eligible local-commute spends. | S78: https://www.axisbank.com/docs/default-source/default-document-library/sosc-credit-cards.pdf | T78: Legacy/current Axis issuer terms accessed 2026-09-09; card discontinued | U78: https://www.axis.bank.in/cards/credit-card/axis-bank-freecharge-plus-credit-card | V78: Official issuer | W78: 2026-09-09 | X78: Second-pass reward/cashback research; populated only from located source material.
A79: Axis Bank | B79: Discontinued | C79: Vistara Axis Bank Signature Credit Card | D79: 4 Maharaja Points per ₹200 on eligible spends. | S79: https://www.axisbank.com/docs/default-source/default-document-library/sosc-credit-cards.pdf | T79: Legacy/current Axis issuer terms accessed 2026-09-09; card discontinued | U79: https://www.axis.bank.in/cards/credit-card | V79: Official issuer | W79: 2026-09-09 | X79: Legacy Vistara co-brand; issuer has announced discontinuation of spends after 31 October 2026, but this rate is current as of 9 September 2026.
A80: Axis Bank | B80: Discontinued | C80: Vistara Axis Bank Credit Card | D80: 2 Maharaja Points per ₹200 on eligible spends. | S80: https://www.axisbank.com/docs/default-source/default-document-library/sosc-credit-cards.pdf | T80: Legacy/current Axis issuer terms accessed 2026-09-09; card discontinued | U80: https://www.axis.bank.in/cards/credit-card/axis-bank-vistara-credit-card | V80: Official issuer | W80: 2026-09-09 | X80: Current as of 9 September 2026; issuer page states spends will be discontinued after 31 October 2026.
A81: Axis Bank | B81: Discontinued | C81: Vistara Axis Bank Infinite Credit Card | D81: 6 Maharaja Points per ₹200 on eligible spends. | S81: https://www.axisbank.com/docs/default-source/default-document-library/sosc-credit-cards.pdf | T81: Legacy/current Axis issuer terms accessed 2026-09-09; card discontinued | U81: https://www.axis.bank.in/cards/credit-card | V81: Official issuer | W81: 2026-09-09 | X81: Legacy Vistara co-brand; current as of 9 September 2026.
A82: Axis Bank | B82: Discontinued | C82: Kwik Axis Bank Credit Card | D82: 2 EDGE REWARD Points per ₹200 on eligible domestic and international spends. | S82: https://www.axisbank.com/docs/default-source/default-document-library/sosc-credit-cards.pdf | T82: Legacy/current Axis issuer terms accessed 2026-09-09; card discontinued | U82: https://www.axis.bank.in/cards/credit-card/axis-bank-kwik-credit-card | V82: Official issuer | W82: 2026-09-09 | X82: Second-pass reward/cashback research; populated only from located source material.
A83: SBI Card | B83: Selectable | C83: CASHBACK SBI Card | D83: 1% cashback on eligible offline spends. | E83: 5% cashback on eligible online spends, subject to current exclusions/caps. | F83: N/A – statement cashback. | S83: https://www.sbicard.com/en/personal/sbi-credit-card.page https://www.sbicard.com/en/most-important-terms-and-conditions.page | T83: Current official product/MITC accessed 2026-09-09; product revised 2026-04-01
A84: SBI Card | B84: Selectable | C84: SimplyCLICK SBI Card | E84: 5X rewards on eligible online spends; 10X rewards at selected online partners under current programme. | K84: ₹499 + taxes (welcome voucher benefit subject to fee realisation). | P84: ₹2,000 vouchers at ₹1 lakh and ₹2 lakh eligible annual online spend thresholds (as published). | R84: ₹500 Amazon gift-card welcome benefit on eligible fee payment/current terms. | S84: https://www.sbicard.com/en/personal/sbi-credit-card.page | T84: Current official card page accessed 2026-09-09
A85: SBI Card | B85: Selectable | C85: Tata Neu Infinity SBI Card | D85: 1.5% NeuCoins on eligible non-Tata retail spends; 1.5% on eligible UPI for RuPay variant, subject to current terms. | E85: 5% NeuCoins on eligible Tata ecosystem spends. | K85: ₹1,499 + taxes (published welcome NeuCoins benefit applies). | O85: Up to 8 domestic lounge visits/year, max 2/quarter, subject to ₹75,000 preceding-quarter spend under current terms. | R85: Welcome benefit of 1,499 NeuCoins under current card programme. | S85: https://www.sbicard.com/en/personal/sbi-credit-card.page | T85: Current official card page accessed 2026-09-09
A86: SBI Card | B86: Selectable | C86: IndiGo SBI Card | E86: 3% BluChip-equivalent earning on eligible IndiGo spends; 2% on eligible hotel/lodging/travel MCC spends under current programme. | P86: Welcome/renewal benefit of 2,500 BluChips under current terms. | S86: https://www.sbicard.com/en/personal/sbi-credit-card.page | T86: Current official card page accessed 2026-09-09
A87: SBI Card | B87: Selectable | C87: IndiGo SBI Card ELITE | E87: 7% BluChip-equivalent earning on eligible IndiGo spends under current programme. | N87: 1.99% | P87: Welcome/renewal benefit includes 5,000 BluChips and one 6E Eats benefit under current terms. | Q87: 1% fuel surcharge waiver subject to current SBI limits; published cap ₹400/statement cycle. | S87: https://www.sbicard.com/en/personal/sbi-credit-card.page | T87: Current official card page accessed 2026-09-09
A88: SBI Card | B88: Selectable | C88: Flipkart SBI Card | E88: Up to 7.5% cashback/value on eligible Flipkart, Myntra and Cleartrip spends under current programme. | L88: Published renewal fee applies; exact fee should be checked on current product page. | M88: Renewal fee waiver at ₹3.5 lakh eligible annual spend under current card terms. | Q88: 1% fuel surcharge waiver subject to current SBI limits; published cap ₹400/statement cycle. | R88: ₹250 Flipkart gift-card welcome benefit on fee realisation under current terms. | S88: https://www.sbicard.com/en/personal/sbi-credit-card.page | T88: Current official card page accessed 2026-09-09
A89: SBI Card | B89: Selectable | C89: Apollo SBI Card SELECT | D89: 1 Reward Point per ₹200 on eligible other spends. | E89: 10 Reward Points per ₹100 on eligible Apollo spends and 2 Reward Points per ₹100 on eligible dining, movies, entertainment and travel. | F89: 1 Reward Point = ₹1 Health Credit for eligible Apollo redemptions, subject to programme rules. | S89: https://www.sbicard.com/en/personal/sbi-credit-card.page | T89: Current official catalogue accessed 2026-09-09 | U89: https://www.sbicard.com/en/personal/sbi-credit-card.page | V89: Official issuer | W89: 2026-09-09 | X89: Second-pass reward/cashback research; populated only from located source material.
A90: SBI Card | B90: Selectable | C90: Tata Neu Plus SBI Card | D90: 1% NeuCoins on eligible non-Tata retail spends; 1% on eligible UPI for RuPay variant. | E90: 2% NeuCoins on eligible Tata ecosystem spends. | K90: ₹499 + taxes | O90: Up to 4 domestic lounge visits/year, max 1/quarter, subject to ₹50,000 preceding-quarter spend under current terms. | R90: Welcome benefit of 499 NeuCoins under current card programme. | S90: https://www.sbicard.com/en/personal/sbi-credit-card.page | T90: Current official card page accessed 2026-09-09
A91: SBI Card | B91: Selectable | C91: KrisFlyer SBI Card | D91: 2 KrisFlyer miles per ₹200 on eligible spends. | E91: 5 KrisFlyer miles per ₹200 on eligible Singapore Airlines and international spends. | S91: https://www.sbicard.com/en/personal/sbi-credit-card.page | T91: Current official catalogue accessed 2026-09-09 | U91: https://www.sbicard.com/en/personal/sbi-credit-card.page | V91: Official issuer | W91: 2026-09-09 | X91: Second-pass reward/cashback research; populated only from located source material.
A92: SBI Card | B92: Selectable | C92: KrisFlyer SBI Card Apex | D92: 6 KrisFlyer miles per ₹200 on eligible spends. | E92: 10 miles per ₹200 on eligible Singapore Airlines spends and 8 per ₹200 on eligible international spends. | S92: https://www.sbicard.com/en/personal/sbi-credit-card.page | T92: Current official catalogue accessed 2026-09-09 | U92: https://www.sbicard.com/en/personal/sbi-credit-card.page | V92: Official issuer | W92: 2026-09-09 | X92: Second-pass reward/cashback research; populated only from located source material.
A93: SBI Card | B93: Selectable | C93: SBI Card Miles Elite | D93: Travel Credits on eligible spends; current product page specifies earn categories. | E93: 6 Travel Credits/₹200 on eligible travel spends under current terms. | P93: Welcome 5,000 Travel Credits; up to 20,000 bonus Travel Credits at ₹12 lakh eligible annual spend. | R93: Travel Credits can be transferred/redeemed to participating airline/hotel/travel/catalogue partners under current terms. | S93: https://www.sbicard.com/en/personal/sbi-credit-card.page | T93: Current official card page accessed 2026-09-09
A94: SBI Card | B94: Selectable | C94: SBI Card MILES PRIME | D94: 2 Travel Credits per ₹200 on eligible spends. | E94: 4 Travel Credits per ₹200 on eligible travel spends. | S94: https://www.sbicard.com/en/personal/sbi-credit-card.page | T94: Current official catalogue accessed 2026-09-09 | U94: https://www.sbicard.com/en/personal/sbi-credit-card.page | V94: Official issuer | W94: 2026-09-09 | X94: Second-pass reward/cashback research; populated only from located source material.
A95: SBI Card | B95: Selectable | C95: SBI Card MILES | D95: 1 Travel Credit per ₹200 on eligible spends. | E95: 2 Travel Credits per ₹200 on eligible travel spends. | S95: https://www.sbicard.com/en/personal/sbi-credit-card.page | T95: Current official catalogue accessed 2026-09-09 | U95: https://www.sbicard.com/en/personal/sbi-credit-card.page | V95: Official issuer | W95: 2026-09-09 | X95: Second-pass reward/cashback research; populated only from located source material.
A96: SBI Card | B96: Selectable | C96: Titan SBI Card | D96: 6 Reward Points per ₹100 on eligible non-Titan spends. | E96: 7.5% value back/cashback on eligible Titan spends; 5% on eligible Mia, CaratLane and Zoya spends; eligible Tanishq spends receive programme-specific voucher/value benefits. | S96: https://www.sbicard.com/en/personal/sbi-credit-card.page | T96: Current official catalogue accessed 2026-09-09 | U96: https://www.sbicard.com/en/personal/sbi-credit-card.page | V96: Official issuer | W96: 2026-09-09 | X96: Second-pass reward/cashback research; populated only from located source material.
A97: SBI Card | B97: Selectable | C97: Reliance SBI Card | D97: 1 Reward Point per ₹100 on eligible other retail spends. | E97: 10 Reward Points per ₹100 at AJIO and JioMart; 5 per ₹100 at other participating Reliance stores and eligible dining/movies. | S97: https://www.sbicard.com/en/personal/sbi-credit-card.page | T97: Current official catalogue accessed 2026-09-09 | U97: https://www.sbicard.com/sbi-card-en/assets/docs/pdf/tnc/reliance-sbi-card-tnc.pdf | V97: Official issuer | W97: 2026-09-09 | X97: Second-pass reward/cashback research; populated only from located source material.
A98: SBI Card | B98: Selectable | C98: Reliance SBI Card PRIME | D98: 2 Reward Points per ₹100 on eligible other spends. | E98: 20 Reward Points per ₹100 at eligible AJIO/JioMart; 10 at other participating Reliance stores; 5 on selected dining/movies/entertainment/domestic-airline/international spends. | F98: 4 Reward Points = ₹1 under the card rewards programme, subject to redemption route. | S98: https://www.sbicard.com/en/personal/sbi-credit-card.page | T98: Current official catalogue accessed 2026-09-09 | U98: https://www.sbicard.com/en/personal/sbi-credit-card.page | V98: Official issuer | W98: 2026-09-09 | X98: Second-pass reward/cashback research; populated only from located source material.
A99: SBI Card | B99: Selectable | C99: SBI Card PULSE | D99: 2 Reward Points/₹100 on eligible base spends under current reward programme. | E99: 10 Reward Points/₹100 (5X) on eligible chemist/pharmacy, sports, dining and movie categories; current merchant/MCC rules apply. | I99: Wallet MCC 6540/6541 excluded from reward earning under current SBI rewards T&C. | L99: ₹1,499 + taxes | P99: ₹1,500 e-voucher on ₹4 lakh eligible annual spend under current terms. | S99: https://www.sbicard.com/en/personal/sbi-credit-card.page https://www.sbicard.com/en/most-important-terms-and-conditions.page | T99: Current official product/reward T&C accessed 2026-09-09
A100: SBI Card | B100: Selectable | C100: BPCL SBI Card | D100: 1 Reward Point per ₹100 on eligible other spends. | E100: 5 Reward Points per ₹100 on eligible grocery, departmental-store, dining and movie spends; 13X total reward earn on eligible BPCL fuel spends. | F100: 4 Reward Points = ₹1. | G100: Accelerated lifestyle-category spend capped at the issuer-defined monthly threshold; BPCL accelerated reward points capped under card T&C. | L100: ₹499 + taxes | M100: Renewal fee reversal at ₹1 lakh eligible annual spend, effective 2026-05-01 under SBI notice. | S100: https://www.sbicard.com/en/personal/sbi-credit-card.page https://www.sbicard.com/en/most-important-terms-and-conditions.page | T100: Fee-waiver revision effective 2026-05-01; official material accessed 2026-09-09 | U100: https://www.sbicard.com/en/personal/sbi-credit-card.page | V100: Official issuer | W100: 2026-09-09 | X100: Second-pass reward/cashback research; populated only from located source material.
...

Sheet README
A1: LedgerKit Credit Card Catalogue Research
A3: Scope
A4: 295 cards across 16 issuers: 249 selectable and 46 discontinued. All rows from the supplied catalogue are retained.
A6: Methodology
A7: • Primary-source first: issuer product pages, current MITC/KFS/schedules, and official cardmember agreements were prioritized.
A8: • Blank cells are intentional. They mean a sufficiently clear official value was not located in the research pass; blanks should not be interpreted as zero, no benefit, or no exclusion.
A9: • For discontinued cards, legacy facts are populated only when official legacy/current-servicing material was found. Historical cards are retained even when their old product page is no longer public.
A10: • Issuer-wide rules are used only where the issuer document explicitly applies them to the card/variant. Co-brand-specific rules are not inferred from generic issuer rules.
A11: • Effective date records a document date when explicit; otherwise it records the official page access date (9 September 2026).
A12: • Fees shown generally exclude GST unless the text explicitly says otherwise. Benefit availability can depend on network variant, spend qualification, account relationship, and issuer changes.

Sheet Coverage
A1: Catalogue Integrity & Coverage
A3: Metric | B3: Value
A4: Total cards | B4: =COUNTA(Catalogue!C2:C296)
A5: Selectable | B5: =COUNTIF(Catalogue!B2:B296,"Selectable")
A6: Discontinued | B6: =COUNTIF(Catalogue!B2:B296,"Discontinued")
A7: Issuers | B7: =COUNTA(A11:A26)
A10: Issuer | B10: Total | C10: Selectable | D10: Discontinued
A11: HDFC Bank | B11: =COUNTIF(Catalogue!$A$2:$A$296,A11) | C11: =COUNTIFS(Catalogue!$A$2:$A$296,A11,Catalogue!$B$2:$B$296,"Selectable") | D11: =COUNTIFS(Catalogue!$A$2:$A$296,A11,Catalogue!$B$2:$B$296,"Discontinued")
A12: ICICI Bank | B12: =COUNTIF(Catalogue!$A$2:$A$296,A12) | C12: =COUNTIFS(Catalogue!$A$2:$A$296,A12,Catalogue!$B$2:$B$296,"Selectable") | D12: =COUNTIFS(Catalogue!$A$2:$A$296,A12,Catalogue!$B$2:$B$296,"Discontinued")
A13: Axis Bank | B13: =COUNTIF(Catalogue!$A$2:$A$296,A13) | C13: =COUNTIFS(Catalogue!$A$2:$A$296,A13,Catalogue!$B$2:$B$296,"Selectable") | D13: =COUNTIFS(Catalogue!$A$2:$A$296,A13,Catalogue!$B$2:$B$296,"Discontinued")
A14: SBI Card | B14: =COUNTIF(Catalogue!$A$2:$A$296,A14) | C14: =COUNTIFS(Catalogue!$A$2:$A$296,A14,Catalogue!$B$2:$B$296,"Selectable") | D14: =COUNTIFS(Catalogue!$A$2:$A$296,A14,Catalogue!$B$2:$B$296,"Discontinued")
A15: Kotak Mahindra Bank | B15: =COUNTIF(Catalogue!$A$2:$A$296,A15) | C15: =COUNTIFS(Catalogue!$A$2:$A$296,A15,Catalogue!$B$2:$B$296,"Selectable") | D15: =COUNTIFS(Catalogue!$A$2:$A$296,A15,Catalogue!$B$2:$B$296,"Discontinued")
A16: IDFC FIRST Bank | B16: =COUNTIF(Catalogue!$A$2:$A$296,A16) | C16: =COUNTIFS(Catalogue!$A$2:$A$296,A16,Catalogue!$B$2:$B$296,"Selectable") | D16: =COUNTIFS(Catalogue!$A$2:$A$296,A16,Catalogue!$B$2:$B$296,"Discontinued")
A17: IndusInd Bank | B17: =COUNTIF(Catalogue!$A$2:$A$296,A17) | C17: =COUNTIFS(Catalogue!$A$2:$A$296,A17,Catalogue!$B$2:$B$296,"Selectable") | D17: =COUNTIFS(Catalogue!$A$2:$A$296,A17,Catalogue!$B$2:$B$296,"Discontinued")
A18: AU Small Finance Bank | B18: =COUNTIF(Catalogue!$A$2:$A$296,A18) | C18: =COUNTIFS(Catalogue!$A$2:$A$296,A18,Catalogue!$B$2:$B$296,"Selectable") | D18: =COUNTIFS(Catalogue!$A$2:$A$296,A18,Catalogue!$B$2:$B$296,"Discontinued")
A19: YES BANK | B19: =COUNTIF(Catalogue!$A$2:$A$296,A19) | C19: =COUNTIFS(Catalogue!$A$2:$A$296,A19,Catalogue!$B$2:$B$296,"Selectable") | D19: =COUNTIFS(Catalogue!$A$2:$A$296,A19,Catalogue!$B$2:$B$296,"Discontinued")
A20: RBL Bank | B20: =COUNTIF(Catalogue!$A$2:$A$296,A20) | C20: =COUNTIFS(Catalogue!$A$2:$A$296,A20,Catalogue!$B$2:$B$296,"Selectable") | D20: =COUNTIFS(Catalogue!$A$2:$A$296,A20,Catalogue!$B$2:$B$296,"Discontinued")
A21: American Express India | B21: =COUNTIF(Catalogue!$A$2:$A$296,A21) | C21: =COUNTIFS(Catalogue!$A$2:$A$296,A21,Catalogue!$B$2:$B$296,"Selectable") | D21: =COUNTIFS(Catalogue!$A$2:$A$296,A21,Catalogue!$B$2:$B$296,"Discontinued")
A22: HSBC India | B22: =COUNTIF(Catalogue!$A$2:$A$296,A22) | C22: =COUNTIFS(Catalogue!$A$2:$A$296,A22,Catalogue!$B$2:$B$296,"Selectable") | D22: =COUNTIFS(Catalogue!$A$2:$A$296,A22,Catalogue!$B$2:$B$296,"Discontinued")
... A26: Federal Bank | B26: =COUNTIF(Catalogue!$A$2:$A$296,A26) | C26: =COUNTIFS(Catalogue!$A$2:$A$296,A26,Catalogue!$B$2:$B$296,"Selectable") | D26: =COUNTIFS(Catalogue!$A$2:$A$296,A26,Catalogue!$B$2:$B$296,"Discontinued")
A29: Requested field | B29: Nonblank rows | C29: Coverage %
A30: Base reward | B30: =COUNTA(Catalogue!D2:D296) | C30: =B30/$B$4
A31: Accelerated rewards | B31: =COUNTA(Catalogue!E2:E296) | C31: =B31/$B$4
A32: Reward-point value | B32: =COUNTA(Catalogue!F2:F296) | C32: =B32/$B$4
A33: Monthly/quarterly/annual caps | B33: =COUNTA(Catalogue!G2:G296) | C33: =B33/$B$4
A34: Minimum transaction | B34: =COUNTA(Catalogue!H2:H296) | C34: =B34/$B$4
A35: Excluded categories/MCCs | B35: =COUNTA(Catalogue!I2:I296) | C35: =B35/$B$4
A36: Excluded merchants | B36: =COUNTA(Catalogue!J2:J296) | C36: =B36/$B$4
A37: Joining fee | B37: =COUNTA(Catalogue!K2:K296) | C37: =B37/$B$4
A38: Annual fee | B38: =COUNTA(Catalogue!L2:L296) | C38: =B38/$B$4
A39: Fee-waiver condition | B39: =COUNTA(Catalogue!M2:M296) | C39: =B39/$B$4
A40: Forex markup | B40: =COUNTA(Catalogue!N2:N296) | C40: =B40/$B$4
A41: Lounge benefits | B41: =COUNTA(Catalogue!O2:O296) | C41: =B41/$B$4
A42: Milestone benefits | B42: =COUNTA(Catalogue!P2:P296) | C42: =B42/$B$4
A43: Fuel surcharge waiver | B43: =COUNTA(Catalogue!Q2:Q296) | C43: =B43/$B$4
A44: Other benefits | B44: =COUNTA(Catalogue!R2:R296) | C44: =B44/$B$4
A45: Official source URL | B45: =COUNTA(Catalogue!S2:S296) | C45: =B45/$B$4
A46: Effective date | B46: =COUNTA(Catalogue!T2:T296) | C46: =B46/$B$4

Sheet Sources
A1: Issuer | B1: Source | C1: Date / status | D1: Official URL | E1: Data / claims used
A2: HDFC Bank | B2: Credit Cards catalogue | C2: Current | D2: https://www.hdfc.bank.in/credit-cards | E2: Card catalogue and card-specific product navigation
A3: ICICI Bank | B3: Credit Cards catalogue | C3: Current | D3: https://www.icicibank.com/personal-banking/cards/credit-card | E3: Current cards and product pages
A4: Axis Bank | B4: Schedule of Charges / KFS | C4: Current | D4: https://www.axisbank.com/docs/default-source/default-document-library/sosc-credit-cards.pdf | E4: Fees, fuel-waiver and transaction-charge rules across card variants
A5: Axis Bank | B5: Cashback Credit Card T&C | C5: Current | D5: https://www.axisbank.com/docs/default-source/ld/axis-bank-cashback-credit-card-tnc.pdf | E5: Cashback earn, caps, exclusions and fee-waiver terms
A6: SBI Card | B6: Credit Cards catalogue | C6: Current | D6: https://www.sbicard.com/en/personal/sbi-credit-card.page | E6: Current card features
A7: SBI Card | B7: Most Important Terms & Conditions | C7: Current | D7: https://www.sbicard.com/en/most-important-terms-and-conditions.page | E7: Issuer fees, charges and card-level conditions
A8: Kotak Mahindra Bank | B8: Credit Cards catalogue | C8: Current | D8: https://www.kotak.bank.in/en/personal-banking/cards/credit-cards.html | E8: Current cards, fees and headline benefits
A9: IDFC FIRST Bank | B9: Credit Cards catalogue | C9: Current | D9: https://www.idfcfirstbank.com/credit-card | E9: Current card comparison and product features
A10: IDFC FIRST Bank | B10: MITC / Fees and Charges | C10: Current | D10: https://www.idfcfirstbank.com/credit-card/fees-and-charges | E10: Joining/annual fees, forex, surcharge and other card terms
A11: IndusInd Bank | B11: Credit Cards catalogue | C11: Current/legacy | D11: https://www.indusind.bank.in/in/en/personal/cards/credit-card.html | E11: Current and retained legacy card feature material
A12: AU Small Finance Bank | B12: Credit Cards catalogue | C12: Current | D12: https://www.au.bank.in/personal-banking/credit-cards | E12: Current cards and product benefits
... A25: Federal Bank | B25: Credit Cards KFS / General Terms | C25: Current | D25: https://www.federalbank.co.in/-/credit-cards-general-terms-and-conditions-1 | E25: Current fees and forex markup for Federal Bank variants
A27: Second-pass reward/cashback sources
A28: Card | B28: Issuer | C28: Reward source type | D28: Reward source URL | E28: Research note
A29: IndianOil HDFC Bank Credit Card | B29: HDFC Bank | C29: Official issuer | D29: https://www.hdfc.bank.in/credit-cards/indianoil-hdfc-bank-credit-card | E29: Second-pass reward/cashback research; populated only from located source material.
A30: Tata Neu Infinity HDFC Bank Credit Card | B30: HDFC Bank | C30: Official issuer | D30: https://www.hdfc.bank.in/credit-cards/tata-neu-infinity-hdfc-bank-credit-card | E30: Second-pass reward/cashback research; populated only from located source material.
A31: HDFC Bank Freedom Credit Card | B31: HDFC Bank | C31: Official issuer | D31: https://www.hdfc.bank.in/credit-cards/freedom-credit-card | E31: Second-pass reward/cashback research; populated only from located source material.
A32: PhonePe HDFC Bank Uno Credit Card | B32: HDFC Bank | C32: Official issuer | D32: https://www.hdfc.bank.in/credit-cards/phonepe-hdfc-bank-uno-credit-card | E32: Second-pass reward/cashback research; populated only from located source material.
A33: PhonePe HDFC Bank Ultimo Credit Card | B33: HDFC Bank | C33: Official issuer | D33: https://www.hdfc.bank.in/credit-cards/phonepe-hdfc-bank-ultimo-credit-card | E33: Second-pass reward/cashback research; populated only from located source material.
A34: HDFC Bank Diners Club Black Metal Edition Credit Card | B34: HDFC Bank | C34: Official issuer | D34: https://v.hdfc.bank.in/htdocs/amp/personal/pay/cards/credit-cards/diners-club-black-metal-edition.html | E34: Second-pass reward/cashback research; populated only from located source material.
A35: HDFC Bank PIXEL Play Credit Card | B35: HDFC Bank | C35: Official issuer | D35: https://www.hdfc.bank.in/content/dam/hdfcbankpws/in/en/personal-banking/discover-products/cards/credit-cards/pixel-play-credit-card/terms-and-conditions-pixel-play-credit-card-16122025.pdf | E35: Second-pass reward/cashback research; populated only from located source material.
A36: HDFC Bank PIXEL Go Credit Card | B36: HDFC Bank | C36: Official issuer | D36: https://www.hdfc.bank.in/credit-cards/pixel-go-credit-card | E36: Second-pass reward/cashback research; populated only from located source material.
A37: HDFC Bank UPI RuPay Credit Card | B37: HDFC Bank | C37: Official issuer | D37: https://www.hdfc.bank.in/credit-cards/hdfc-bank-upi-rupay-credit-card | E37: Second-pass reward/cashback research; populated only from located source material.
A38: HDFC Bank Regalia Gold Credit Card | B38: HDFC Bank | C38: Official issuer | D38: https://www.hdfc.bank.in/blogs/regalia-gold-credit-card/redeem-regalia-gold-credit-card-reward-points | E38: Second-pass reward/cashback research; populated only from located source material.
A39: Tata Neu Plus HDFC Bank Credit Card | B39: HDFC Bank | C39: Official issuer | D39: https://www.hdfc.bank.in/credit-cards/tata-neu-plus-hdfc-bank-credit-card | E39: Second-pass reward/cashback research; populated only from located source material.
... A239: Scapia Federal Bank Credit Card | B239: Federal Bank | C239: Official issuer / co-brand | D239: https://www.federal.bank.in/documents/d/guest/cardholder_agreement-v11-30_04_26 | E239: Second-pass reward/cashback research; populated only from located source material.

Sheet Reward Research
A1: Reward / cashback second-pass research
A2: Research date | B2: 2026-09-09
A3: Original rows with both Base reward and Accelerated rewards blank | B3: 211
A4: Rows with at least one reward/cashback field recovered | B4: 211
A5: Rows with both base and accelerated fields populated | B5: 171
A6: Rows using a source labelled credible secondary | B6: 7
A7: Rows with intentionally descriptive/non-numeric reward wording | B7: 12
A9: Issuer | B9: Target rows | C9: Recovered at least one | D9: Credible-secondary rows
A10: AU Small Finance Bank | B10: 23 | C10: 23 | D10: 3
A11: American Express India | B11: 1 | C11: 1 | D11: 0
A12: Axis Bank | B12: 38 | C12: 38 | D12: 2
A13: BOBCARD | B13: 11 | C13: 11 | D13: 0
A14: Federal Bank | B14: 1 | C14: 1 | D14: 0
A15: HDFC Bank | B15: 17 | C15: 17 | D15: 0
A16: HSBC India | B16: 1 | C16: 1 | D16: 0
A17: ICICI Bank | B17: 17 | C17: 17 | D17: 0
A18: IDFC FIRST Bank | B18: 8 | C18: 8 | D18: 0
A19: IndusInd Bank | B19: 13 | C19: 13 | D19: 0
A20: Kotak Mahindra Bank | B20: 6 | C20: 6 | D20: 0
A21: RBL Bank | B21: 37 | C21: 37 | D21: 1
... A24: YES BANK | B24: 16 | C24: 16 | D24: 1
